pykano/__init__.py
pykano/ktools.py
pykano-0.0.4.dist-info/LICENSE
pykano-0.0.4.dist-info/METADATA
pykano-0.0.4.dist-info/WHEEL
pykano-0.0.4.dist-info/top_level.txt
pykano-0.0.4.dist-info/RECORD
