Metadata-Version: 2.1
Name: pykano
Version: 0.0.4
Summary: kano tools for python3
Home-page: http://www.rapfan.cn
Author: kano
Author-email: sweetyrice@gmail.com
License: MIT
Platform: UNKNOWN
